README.md
setup.py
PySwapper/__init__.py
PySwapper.egg-info/PKG-INFO
PySwapper.egg-info/SOURCES.txt
PySwapper.egg-info/dependency_links.txt
PySwapper.egg-info/top_level.txt