Metadata-Version: 1.1
Name: PySwapper
Version: 1.1.2
Summary: stores variables in disk.
Home-page: https://github.com/mohammad-sh-845/
Author: mohammad-sh-845
Author-email: mohammad85sh.ir@gmail.com
License: MIT
Download-URL: https://github.com/mohammad-sh-845/swapper/archive/refs/tags/1.0.tar.gz
Keywords: swap,disk
Platform: UNKNOWN
Classifier: Development Status :: 4 - Beta
Classifier: Topic :: Software Development :: Build Tools
Classifier: License :: OSI Approved :: MIT License
Classifier: Programming Language :: Python :: 3
Classifier: Programming Language :: Python :: 3.4
Classifier: Programming Language :: Python :: 3.5
Classifier: Programming Language :: Python :: 3.6
Classifier: Programming Language :: Python :: 3.7
Classifier: Programming Language :: Python :: 3.8
